l0n0lnat/ID生成.py
l0n0lnat/__init__.py
l0n0lnat/本地.py
l0n0lnat/消息.py
l0n0lnat/远端.py
l0n0lnat/通用.py
l0n0lnat-3.1.0.dist-info/METADATA
l0n0lnat-3.1.0.dist-info/WHEEL
l0n0lnat-3.1.0.dist-info/entry_points.txt
l0n0lnat-3.1.0.dist-info/top_level.txt
l0n0lnat-3.1.0.dist-info/RECORD
