Metadata-Version: 2.1
Name: l0n0lnat
Version: 3.1.0
Summary: Add your description here
Requires-Python: >=3.8
Requires-Dist: l0n0ltcp >=2.0.2
